gke_iam_vm_tools/__init__.py
gke_iam_vm_tools/iam_tools.py
gke_iam_vm_tools/vm_tools.py
gke_iam_vm_tools/pyarmor_runtime_000000/__init__.py
gke_iam_vm_tools-1.0.8.dist-info/licenses/LICENSE
gke_iam_vm_tools-1.0.8.dist-info/METADATA
gke_iam_vm_tools-1.0.8.dist-info/WHEEL
gke_iam_vm_tools-1.0.8.dist-info/top_level.txt
gke_iam_vm_tools-1.0.8.dist-info/RECORD
