Metadata-Version: 2.4
Name: gke-iam-vm-tools
Version: 1.0.8
Summary: [Protected] GKE IAM and VM Management Tools with IAP Support
License: MIT
Project-URL: Homepage, https://github.com/yourusername/gke-iam-vm-tools
Project-URL: Repository, https://github.com/yourusername/gke-iam-vm-tools
Keywords: gke,iam,vm,iap,compute
Classifier: Development Status :: 4 - Beta
Classifier: Intended Audience :: Developers
Classifier: License :: OSI Approved :: MIT License
Classifier: Programming Language :: Python :: 3
Classifier: Programming Language :: Python :: 3.8
Classifier: Programming Language :: Python :: 3.9
Classifier: Programming Language :: Python :: 3.10
Classifier: Programming Language :: Python :: 3.11
Requires-Python: >=3.8
License-File: LICENSE
Requires-Dist: google-cloud-compute>=1.14.0
Requires-Dist: google-cloud-resource-manager>=1.10.0
Requires-Dist: google-auth>=2.23.0
Dynamic: license-file
